oect_transfer/__init__.py
oect_transfer/transfer.py
oect_transfer-0.4.2.dist-info/licenses/LICENSE
oect_transfer-0.4.2.dist-info/METADATA
oect_transfer-0.4.2.dist-info/WHEEL
oect_transfer-0.4.2.dist-info/top_level.txt
oect_transfer-0.4.2.dist-info/RECORD
