Metadata-Version: 2.4
Name: oect-transfer
Version: 0.4.2
Summary: Minimal OECT transfer-curve utilities
Author-email: lidonghao <lidonghao100@outlook.com>
License: MIT
Project-URL: Homepage, https://github.com/yourusername/my-package
Project-URL: Documentation, https://my-package.readthedocs.io/
Project-URL: Repository, https://github.com/yourusername/my-package.git
Project-URL: Bug Tracker, https://github.com/yourusername/my-package/issues
Keywords: oect,transfer
Classifier: Intended Audience :: Science/Research
Classifier: License :: OSI Approved :: MIT License
Classifier: Programming Language :: Python :: 3
Classifier: Topic :: Scientific/Engineering :: Visualization
Requires-Python: >=3.8
License-File: LICENSE
Requires-Dist: numpy>=1.23
Provides-Extra: dev
Requires-Dist: black>=22.0; extra == "dev"
Requires-Dist: flake8>=4.0; extra == "dev"
Requires-Dist: mypy>=0.950; extra == "dev"
Requires-Dist: build; extra == "dev"
Provides-Extra: docs
Requires-Dist: sphinx>=4.0; extra == "docs"
Requires-Dist: sphinx-rtd-theme>=1.0; extra == "docs"
Dynamic: license-file
